[{"link_text":"Disassembly of Pokémon Red","link":"https://bitbucket.org/iimarckus/pokered/src","source":"bitbucket.org","points":"149","comments":"31","submitter":"kanzure","date":1326757972,"id":"3473111","homepage":false},{"link_text":"While CEOs are scrubbing toilets, CTOs are building things","link":"http://startupnorth.ca/2012/01/16/while-startup-ceos-are-scrubbing-toilets-ctos-are-building-things/","source":"startupnorth.ca","points":"7","comments":"0","submitter":"macwarlock","date":1326757673,"id":"3472958","homepage":false},{"link_text":"Amber: Smalltalk in the browser","link":"http://amber-lang.net/index.html","source":"amber-lang.net","points":"12","comments":"0","submitter":"beza1e1","date":1326757673,"id":"3472901","homepage":false},{"link_text":"FreeBSD now available on all EC2 instance types","link":"http://www.daemonology.net/blog/2012-01-16-FreeBSD-now-on-all-EC2-instance-types.html","source":"daemonology.net","points":"139","comments":"30","submitter":"cperciva","date":1326755285,"id":"3472984","homepage":false},{"link_text":"What It’s Really Like to Work at Google","link":"http://www.lockergnome.com/social/2012/01/16/what-its-really-like-to-work-at-google/","source":"lockergnome.com","points":"233","comments":"145","submitter":"kellyhclay","date":1326754072,"id":"3472928","homepage":false},{"link_text":"Building the next generation file system for Windows: ReFS","link":"http://blogs.msdn.com/b/b8/archive/2012/01/16/building-the-next-generation-file-system-for-windows-refs.aspx","source":"msdn.com","points":"116","comments":"41","submitter":"jhack","date":1326753773,"id":"3472857","homepage":false},{"link_text":"My girlfriend cooks lunch for everybody in my startup, she made a blog about it.","link":"http://thefoodforstartups.com/","source":"thefoodforstartups.com","points":"34","comments":"16","submitter":"jpadilla_","date":1326753173,"id":"3472880","homepage":false},{"link_text":"Poll: What is your favorite programming language?","link":"http://news.ycombinator.com/item?id=3472683","points":"8","comments":"9","submitter":"gnosis","date":1326752873,"id":"3472683","homepage":false},{"link_text":"Luma Labs put out of business by the USPTO","link":"http://boingboing.net/2012/01/16/how-usptos-recklessness-dest.html","source":"boingboing.net","points":"5","comments":"2","submitter":"gerggerg","date":1326751372,"id":"3472571","homepage":false},{"link_text":"Show HN: Notification Control my weekend project - Email notification setup","link":"http://notificationcontrol.com/","source":"notificationcontrol.com","points":"26","comments":"12","submitter":"benjlang","date":1326751072,"id":"3472580","homepage":false},{"link_text":"Faster TDD feedback with tmux, tslime.vim, and turbux.vim","link":"http://joshuadavey.com/post/15619414829/faster-tdd-feedback-with-tmux-tslime-vim-and","source":"joshuadavey.com","points":"59","comments":"10","submitter":"lucaspiller","date":1326750172,"id":"3472446","homepage":false},{"link_text":"A Weekend with Z Shell","link":"http://avalonstar.com/journal/2012/jan/16/a-weekend-with-z-shell/","source":"avalonstar.com","points":"28","comments":"9","submitter":"revyver","date":1326749572,"id":"3472330","homepage":false},{"link_text":"What did people crowdsource in 2011?","link":"http://blog.mobileworks.com/what-did-people-crowdsource-in-2011","source":"mobileworks.com","points":"17","comments":"3","submitter":"anandkulkarni","date":1326748673,"id":"3472432","homepage":false},{"link_text":"Migrating SimpleGeo Customers to Parse: Idea to Production in One Day","link":"http://blog.parse.com/2012/01/16/migrating-simplegeo-customers/","source":"parse.com","points":"14","comments":"1","submitter":"csmajorfive","date":1326748673,"id":"3472386","homepage":false},{"link_text":"Stack Exchange grew from 16M to 32M uniques in 2011","link":"http://stackexchange.com/state-of-the-stack","source":"stackexchange.com","points":"70","comments":"32","submitter":"kamens","date":1326747473,"id":"3472334","homepage":false},{"link_text":"Purely Functional Retrogames","link":"http://prog21.dadgum.com/23.html","source":"dadgum.com","points":"73","comments":"13","submitter":"aycangulez","date":1326747473,"id":"3472272","homepage":false},{"link_text":"How to Mirror Wikipedia","link":"http://www.igeek.co.za/2009/10/16/how-to-mirror-wikipedia/","source":"igeek.co.za","points":"26","comments":"7","submitter":"jvoorhis","date":1326747173,"id":"3472155","homepage":false},{"link_text":"JSON will be a core type in PostgreSQL 9.2","link":"http://people.planetpostgresql.org/andrew/index.php?/archives/244-Under-the-wire.html","source":"planetpostgresql.org","points":"347","comments":"41","submitter":"zmanji","date":1326745372,"id":"3472177","homepage":false},{"link_text":"While startup CEOs are scrubbing toilets, CTOs are building things","link":"http://startupnorth.ca/2012/01/16/while-startup-ceos-are-scrubbing-toilets-ctos-are-building-things","source":"startupnorth.ca","points":"9","comments":"1","submitter":"jmacd","date":1326745072,"id":"3472179","homepage":false},{"link_text":"HelloFax (YC W11) is hiring a VP of Marketing & Business Development","link":"http://news.ycombinator.com/item?id=3472187","points":"","comments":"","submitter":"","date":1326744472,"id":"3472187","homepage":false},{"link_text":"Sorry state of dynamic libraries on Linux","link":"http://www.macieira.org/blog/2012/01/sorry-state-of-dynamic-libraries-on-linux","source":"macieira.org","points":"88","comments":"26","submitter":"d0mine","date":1326743572,"id":"3472142","homepage":false},{"link_text":"Startup Rage Comics","link":"http://startuprage.com/?comics","source":"startuprage.com","points":"12","comments":"1","submitter":"vecter","date":1326743572,"id":"3472062","homepage":false},{"link_text":"A 14-year-old could build 1998's Google using her Dad's credit card","link":"http://paulbohm.com/2012/01/16/a-14-year-old-could-build-1998s-google-using-her-dads-credit-card/","source":"paulbohm.com","points":"119","comments":"70","submitter":"enki","date":1326743274,"id":"3472098","homepage":false},{"link_text":"How I imagine Launch pages to look like","link":"http://hushflow.com/","source":"hushflow.com","points":"11","comments":"5","submitter":"Santas","date":1326742073,"id":"3471981","homepage":false},{"link_text":"Many Core processors: Everything You Know (about Parallel Programming) Is Wrong","link":"http://my-inner-voice.blogspot.com/2012/01/many-core-processors-everything-you.html","source":"my-inner-voice.blogspot.com","points":"175","comments":"97","submitter":"miha123","date":1326742073,"id":"3471970","homepage":false},{"link_text":"Show HN: IndexTank's search API will live on at Searchify","link":"http://www.searchify.com/","source":"searchify.com","points":"17","comments":"7","submitter":"mthreat","date":1326739672,"id":"3471814","homepage":false},{"link_text":"World Bank Assumes Control of Google Map Data","link":"http://www.readwriteweb.com/archives/world_bank_assumes_control_of_google_map_data.php#.TxRodwAtrPw.hackernews","source":"readwriteweb.com","points":"5","comments":"0","submitter":"jonmwords","date":1326738472,"id":"3471732","homepage":false},{"link_text":"How to write a hackernews comment","link":"http://blog.piasetzki.name/post/15940029463/how-to-write-a-hackernews-comment","source":"piasetzki.name","points":"13","comments":"4","submitter":"jpiasetz","date":1326738172,"id":"3471751","homepage":false},{"link_text":"Wikipedia to Shut Down on Wednesday to Protest SOPA","link":"http://thenextweb.com/insider/2012/01/16/wikipedia-will-shut-down-for-24-hours-on-wednesday-to-protest-against-sopa/?utm_source=feedburner&utm_medium=feed&utm_campaign=Feed%3A+TheNextWeb+%28The+Next+Web+All+Stories%29","source":"thenextweb.com","points":"933","comments":"190","submitter":"minecraftman","date":1326738172,"id":"3471726","homepage":false},{"link_text":"Nearly 1000 of NY Tech protesting Senators on PIPA this Wed - join us, Valley","link":"https://plus.google.com/u/0/113164038788726940319/posts/5sxZg1pHgQ7","source":"google.com","points":"193","comments":"10","submitter":"kn0thing","date":1326737273,"id":"3471671","homepage":false},{"link_text":"Are smart people ugly? The Explainer's 2011 Question of the Year","link":"http://www.slate.com/articles/health_and_science/explainer/2012/01/are_smart_people_ugly_the_explainer_s_2011_question_of_the_year_.single.html","source":"slate.com","points":"9","comments":"3","submitter":"ALee","date":1326737273,"id":"3471540","homepage":false},{"link_text":"Is Your DBA Lying to You?","link":"http://thomaslarock.com/2012/01/is-your-dba-lying-to-you/","source":"thomaslarock.com","points":"8","comments":"2","submitter":"ListMistress","date":1326735773,"id":"3471564","homepage":false},{"link_text":"Microsoft mandating Secure Boot on ARM, making Linux installs difficult","link":"http://arstechnica.com/#!/business/news/2012/01/microsoft-mandating-secure-boot-on-arm-making-linux-installs-difficult.ars","source":"arstechnica.com","points":"114","comments":"43","submitter":"shawndumas","date":1326735472,"id":"3471546","homepage":false},{"link_text":"Sarah Lacy launches PandoDaily (with former Techcrunch writers)","link":"http://pandodaily.com/2012/01/16/why-i-started-pandodaily/","source":"pandodaily.com","points":"68","comments":"54","submitter":"diego","date":1326735176,"id":"3471468","homepage":false},{"link_text":"Show HN: DirtyShare, Pure JavaScript P2P File Sharing (in Node.js + Socket.io)","link":"http://gun.io/blog/dirtyshare-pure-javascript-peer-to-peer-p2p-file-sharing-nodejs-socketio/","source":"gun.io","points":"69","comments":"24","submitter":"Mizza","date":1326733972,"id":"3471405","homepage":false},{"link_text":"NodeUp Eleven - Database Deep Dive","link":"http://nodeup.com/eleven","source":"nodeup.com","points":"9","comments":"0","submitter":"dscape","date":1326733373,"id":"3471287","homepage":false},{"link_text":"A Koan: Anecdote from my time at Facebook","link":"http://blog.garethmacleod.com/a-koan","source":"garethmacleod.com","points":"14","comments":"5","submitter":"reso","date":1326732734,"id":"3471259","homepage":false},{"link_text":"TinyProj Shuts Down, Users Sent To TechStars GroupTalent","link":"http://techcrunch.com/2012/01/16/tinyproj-shuts-down-users-sent-to-techstars-grad-grouptalent-instead/","source":"techcrunch.com","points":"37","comments":"19","submitter":"FluidDjango","date":1326732734,"id":"3471130","homepage":false},{"link_text":"A Design Primer for Engineers","link":"http://www.randsinrepose.com/archives/2012/01/16/a_design_primer_for_engineers.html","source":"randsinrepose.com","points":"117","comments":"5","submitter":"filament","date":1326732434,"id":"3471022","homepage":false},{"link_text":"Blogging With Emacs","link":"http://twitch.nervestaple.com/2011/10/09/blogging_with_emacs/","source":"nervestaple.com","points":"73","comments":"20","submitter":"mofeeta","date":1326732134,"id":"3471214","homepage":false},{"link_text":"Garbage collection with Automatic Resource Management in Java 7","link":"http://javawithswaranga.blogspot.com/2011/06/garbage-collection-with-automatic.html","source":"javawithswaranga.blogspot.com","points":"18","comments":"18","submitter":"JavaTutorial","date":1326730335,"id":"3470997","homepage":false},{"link_text":"Show HN: Vesper, a plug and play Ruby web framework (Sinatra + Rack + Plugins)","link":"http://vesperapps.com/","source":"vesperapps.com","points":"40","comments":"16","submitter":"jarrodtaylor","date":1326729434,"id":"3471017","homepage":false},{"link_text":"Review my startup - Lean Domain Search: The fastest way to find a domain name","link":"http://www.leandomainsearch.com","source":"leandomainsearch.com","points":"169","comments":"150","submitter":"matt1","date":1326729135,"id":"3470977","homepage":false},{"link_text":"Using Hadoop and HBase with Clojure","link":"http://twitch.nervestaple.com/2012/01/12/clojure-hbase/","source":"nervestaple.com","points":"67","comments":"8","submitter":"cmiles74","date":1326729135,"id":"3470954","homepage":false},{"link_text":"JQ.Mobi Is A Mobile-Optimized HTML5 Rewrite Of the JQuery Framework","link":"http://www.readwriteweb.com/mobile/2012/01/jqmobi-is-a-mobile-optimized-h.php#.TxRDA8sY9vc.hackernews","source":"readwriteweb.com","points":"58","comments":"38","submitter":"werencole","date":1326729135,"id":"3470946","homepage":false},{"link_text":"Nokia sells essential GSM patents to patent troll","link":"http://www.intomobile.com/2012/01/16/nokia-sells-over-450-patents-some-them-deemed-essential-gsm-patent-troll/","source":"intomobile.com","points":"7","comments":"7","submitter":"nextparadigms","date":1326728834,"id":"3470774","homepage":false},{"link_text":"CloudMine Introduces Geospatial Object Querying","link":"http://blog.cloudmine.me/post/15791739158/geoquerying","source":"cloudmine.me","points":"45","comments":"14","submitter":"mweil","date":1326728534,"id":"3470838","homepage":false},{"link_text":"An Ambitious Plan for Putting Kickstarter Out of Business","link":"http://www.mrteacup.org/post/an-ambitious-plan-for-putting-kickstarter-out-of-business.html","source":"mrteacup.org","points":"16","comments":"17","submitter":"KenjiCrosland","date":1326728243,"id":"3470853","homepage":false},{"link_text":"ActiveShell: A Shell for the Web","link":"http://inimino.org/~inimino/blog/shell_for_the_web","source":"inimino.org","points":"37","comments":"10","submitter":"inimino","date":1326728243,"id":"3470846","homepage":false},{"link_text":"Oracle and the Java Ecosystem","link":"http://www.infoq.com/articles/oracle-java-ecosystem","source":"infoq.com","points":"3","comments":"4","submitter":"pron","date":1326728243,"id":"3470843","homepage":false},{"link_text":"On the Usability of Codecademy","link":"http://programmingzen.com/2012/01/16/on-the-usability-of-codecademy/","source":"programmingzen.com","points":"246","comments":"81","submitter":"acangiano","date":1326727936,"id":"3470900","homepage":false},{"link_text":"Trust is Fragile","link":"http://37signals.com/svn/posts/3078-trust-is-fragile","source":"37signals.com","points":"263","comments":"105","submitter":"jaxonrice","date":1326727334,"id":"3470876","homepage":false},{"link_text":"What Canadians can do to fight SOPA/PIPA","link":"http://www.kentfenwick.ca/","source":"kentfenwick.ca","points":"22","comments":"9","submitter":"kentf","date":1326726735,"id":"3470788","homepage":false},{"link_text":"When to expect the next Mac Pro models to arrive.","link":"http://www.marco.org/2012/01/16/why-the-video-pros-are-moving-away-from-apple","source":"marco.org","points":"15","comments":"3","submitter":"AndrewDucker","date":1326726735,"id":"3470700","homepage":false},{"link_text":"Making Love to Webkit","link":"http://acko.net/blog/making-love-to-webkit/","source":"acko.net","points":"303","comments":"45","submitter":"robert-boehnke","date":1326725834,"id":"3470736","homepage":false},{"link_text":"IOS app store has created unrealistic pricing expectations","link":"http://appcubby.com/blog/5-is-the-new-10/","source":"appcubby.com","points":"23","comments":"34","submitter":"kgutteridge","date":1326725534,"id":"3470672","homepage":false},{"link_text":"Hacker News: Our Tiny Charity Desperately Needs Your Help","link":"http://adsbycoffee.tumblr.com/post/15938460759/hackernewshelp","source":"adsbycoffee.tumblr.com","points":"41","comments":"38","submitter":"kanebennett","date":1326724934,"id":"3470723","homepage":false},{"link_text":"Ubuntu Logo with CSS","link":"http://cssdeck.com/item/76/ubuntu-logo-css","source":"cssdeck.com","points":"7","comments":"0","submitter":"macco","date":1326724334,"id":"3470622","homepage":false},{"link_text":"The iOS Beginner blog series","link":"http://kentnguyen.com/ios/ios-beginner-series-intro/","source":"kentnguyen.com","points":"73","comments":"11","submitter":"dqminh","date":1326723434,"id":"3470633","homepage":false},{"link_text":"The Internet wins: SOPA has been shelved, but we must remain vigilant","link":"http://www.extremetech.com/computing/114045-the-internet-wins-sopa-has-been-shelved-but-we-must-remain-vigilant","source":"extremetech.com","points":"72","comments":"16","submitter":"mrsebastian","date":1326723134,"id":"3470448","homepage":false},{"link_text":"Offensive URL \"shortner\"","link":"http://offensiveurl.me/","source":"offensiveurl.me","points":"8","comments":"0","submitter":"chadfowler","date":1326722235,"id":"3470603","homepage":false},{"link_text":"PHP to Objective C, where are the parameters?","link":"http://kentnguyen.com/ios/ios-beginner-series-function-names/","source":"kentnguyen.com","points":"20","comments":"25","submitter":"kentnguyen","date":1326721034,"id":"3470518","homepage":false},{"link_text":"Django Software Foundation announces membership drive","link":"https://www.djangoproject.com/weblog/2012/jan/16/dsf-membership-drive-2012/","source":"djangoproject.com","points":"50","comments":"4","submitter":"freakboy3742","date":1326718635,"id":"3470441","homepage":false},{"link_text":"Remote Debugging Django (mod_wsgi) Applications","link":"http://blueprintforge.com/blog/2012/01/16/remote-debugging-django-mod-wsgi-applications/","source":"blueprintforge.com","points":"30","comments":"2","submitter":"motter","date":1326717735,"id":"3470353","homepage":false},{"link_text":"Website outages and blackouts the right way","link":"https://plus.google.com/u/0/115984868678744352358/posts/Gas8vjZ5fmB","source":"google.com","points":"324","comments":"57","submitter":"amirmc","date":1326717134,"id":"3470396","homepage":false},{"link_text":"Defriending My Rapist","link":"http://opinionator.blogs.nytimes.com/2012/01/13/defriending-my-rapist/?ref=opinion","source":"nytimes.com","points":"24","comments":"0","submitter":"FluidDjango","date":1326717134,"id":"3470334","homepage":false},{"link_text":"Hiring your first employee- a UK guide","link":"http://blog.crispyfriedsoftware.com/post/14179700393/hiring-your-first-uk-employee","source":"crispyfriedsoftware.com","points":"68","comments":"16","submitter":"tomgallard","date":1326716537,"id":"3470309","homepage":false},{"link_text":"Automatically populating .ssh/known_hosts","link":"http://www.daemonology.net/blog/2012-01-16-automatically-populating-ssh-known-hosts.html","source":"daemonology.net","points":"61","comments":"6","submitter":"cperciva","date":1326716537,"id":"3470284","homepage":false},{"link_text":"Android Ice Cream Sandwich PSD startkit","link":"http://www.androiddesign.info","source":"androiddesign.info","points":"92","comments":"9","submitter":"josefrichter","date":1326716234,"id":"3470360","homepage":false},{"link_text":"DataLossDB: A database of breached websites","link":"http://datalossdb.org/","source":"datalossdb.org","points":"11","comments":"3","submitter":"nodata","date":1326716234,"id":"3470273","homepage":false},{"link_text":"Data Mining: Finding Similar Items and Users","link":"http://bionicspirit.com/blog/2012/01/16/cosine-similarity-euclidean-distance.html","source":"bionicspirit.com","points":"78","comments":"20","submitter":"bad_user","date":1326715934,"id":"3470225","homepage":false},{"link_text":"Would Transparency In Company Financials Increase (Disruptive) Innovation?","link":"http://www.arcticstartup.com/2012/01/16/would-transparency-in-company-financials-increase-innovation","source":"arcticstartup.com","points":"3","comments":"1","submitter":"vilpponen","date":1326713535,"id":"3470241","homepage":false},{"link_text":"Open-access textbook for knowledge-based AI","link":"http://www.ida.liu.se/ext/aica/","source":"liu.se","points":"5","comments":"0","submitter":"gmodena","date":1326713234,"id":"3470027","homepage":false},{"link_text":"ArsDigita University: Lectures & courseware from intensive MIT CS program","link":"http://aduni.org/courses/","source":"aduni.org","points":"39","comments":"10","submitter":"nosignal","date":1326712034,"id":"3470195","homepage":false},{"link_text":"Switching Sol Trader from Ruby to C++: one week on","link":"http://chrismdp.github.com/2012/01/switching-sol-trader-from-ruby-to-c-plus-plus-one-week-on/","source":"github.com","points":"44","comments":"12","submitter":"chrismdp","date":1326711435,"id":"3470164","homepage":false},{"link_text":"JSTS Topology Suite","link":"https://github.com/bjornharrtell/jsts","source":"github.com","points":"5","comments":"0","submitter":"jenhsun","date":1326711134,"id":"3470064","homepage":false},{"link_text":"IT Managment Machiavelli Style","link":"http://venturevillage.eu/the-samwer-way-according-to-machiavelli-1","source":"venturevillage.eu","points":"6","comments":"1","submitter":"missy","date":1326711134,"id":"3470043","homepage":false},{"link_text":"SOPA 'shelved' until consensus is found","link":"http://www.washingtonmonthly.com/political-animal/2012_01/putting_sopa_on_a_shelf034765.php","source":"washingtonmonthly.com","points":"383","comments":"95","submitter":"Geep","date":1326706635,"id":"3470020","homepage":false},{"link_text":"Chromium core security principles","link":"http://www.chromium.org/Home/chromium-security/core-principles","source":"chromium.org","points":"3","comments":"0","submitter":"neic","date":1326706635,"id":"3469852","homepage":false},{"link_text":"Extreme Minimalism: this guy owns just 15 things","link":"http://andrewhy.de/extreme-minimalism/","source":"andrewhy.de","points":"182","comments":"189","submitter":"wgx","date":1326705434,"id":"3469927","homepage":false},{"link_text":"Because I forgot to set my DVR, I'm a pirate.","link":"http://rondam.blogspot.com/2012/01/absurdity-of-online-piracy.html","source":"rondam.blogspot.com","points":"24","comments":"5","submitter":"lisper","date":1326704234,"id":"3469845","homepage":false},{"link_text":"Science Can Neither Explain Nor Deny the Awesomeness of This Sledding Crow","link":"http://www.theatlantic.com/technology/archive/2012/01/science-can-neither-explain-nor-deny-the-awesomeness-of-this-sledding-crow/251395/","source":"theatlantic.com","points":"53","comments":"31","submitter":"latchkey","date":1326703035,"id":"3469830","homepage":false},{"link_text":"What happened to Multiverse? The inside story of Firefly MMO closure","link":"http://venturebeat.com/2012/01/12/what-happened-to-multiverse/","source":"venturebeat.com","points":"4","comments":"0","submitter":"rhufnagel","date":1326702734,"id":"3469740","homepage":false},{"link_text":"It Has Begun - Singapore Considering Following USA's Lead With SOPA/PIPA","link":"https://www.facebook.com/k.shanmugam.page/posts/147669282014158","source":"facebook.com","points":"48","comments":"26","submitter":"iantimothy","date":1326702268,"id":"3469745","homepage":false},{"link_text":"AWS Free Usage Tier now Includes Microsoft Windows on EC2","link":"http://aws.typepad.com/aws/2012/01/aws-free-usage-tier-now-includes-microsoft-windows-on-ec2.html","source":"aws.typepad.com","points":"97","comments":"35","submitter":"jeffbarr","date":1326702268,"id":"3469706","homepage":false},{"link_text":"Login to your Google account by scanning a QR code","link":"https://accounts.google.com/sesame","source":"google.com","points":"204","comments":"65","submitter":"dannyr","date":1326702268,"id":"3469692","homepage":false},{"link_text":"Russia’s Failed Mars Probe Crashes Into Pacific","link":"http://www.nytimes.com/2012/01/16/science/space/russias-phobos-grunt-mars-probe-crashes-into-pacific.html?_r=1","source":"nytimes.com","points":"18","comments":"16","submitter":"diwank","date":1326693749,"id":"3469493","homepage":false},{"link_text":"A Million Pageviews, Thousands of Dollars Poorer, and Still Countlessly Richer","link":"http://danwin.com/2012/01/a-million-pageviews-thousands-of-dollars-poorer-and-still-countlessly-richer/","source":"danwin.com","points":"57","comments":"31","submitter":"danso","date":1326693749,"id":"3469440","homepage":false},{"link_text":"Startup is Vision","link":"http://www.startuplessonslearned.com/2011/11/startup-is-vision.html","source":"startuplessonslearned.com","points":"3","comments":"0","submitter":"zyfo","date":1326693449,"id":"3469418","homepage":false},{"link_text":"Everything You Need to Know About Wall Street in One Brief Tale","link":"http://www.rollingstone.com/politics/blogs/taibblog/everything-you-need-to-know-about-wall-street-in-one-brief-tale-20120113","source":"rollingstone.com","points":"22","comments":"4","submitter":"aliston","date":1326693150,"id":"3469451","homepage":false},{"link_text":"Designing for the 99%","link":"http://jm90403.com/2012/01/16/designing-for-the-99/","source":"jm90403.com","points":"42","comments":"8","submitter":"cemregr","date":1326692850,"id":"3469480","homepage":false},{"link_text":"Commenting, community deterioration, and Hacker News","link":"http://jseliger.com/2012/01/15/commenting-community-deterioration-and-hacker-news/","source":"jseliger.com","points":"204","comments":"113","submitter":"jseliger","date":1326691649,"id":"3469453","homepage":false},{"link_text":"Harvard Statistics 110: Introduction to Probability, on iTunes","link":"http://itunes.apple.com/us/itunes-u/statistics-110-introduction/id495213607","source":"apple.com","points":"153","comments":"42","submitter":"DanielRibeiro","date":1326689249,"id":"3469393","homepage":false},{"link_text":"Show HN: Collection of CSS Creations","link":"http://cssdeck.com","source":"cssdeck.com","points":"161","comments":"36","submitter":"binarydreams","date":1326688351,"id":"3469347","homepage":false},{"link_text":"Aussie wunderkind gets $US250k for technology that could revolutionise web ","link":"http://www.theage.com.au/digital-life/smartphone-apps/aussie-wunderkind-gets-us250k-for-technology-that-could-revolutionise-web-20120113-1pz35.html","source":"theage.com.au","points":"46","comments":"29","submitter":"nreece","date":1326686849,"id":"3469096","homepage":false},{"link_text":"IBM smashes Moore's Law, cuts bit size to 12 atoms","link":"http://www.computerworld.com/s/article/9223396/IBM_smashes_Moore_s_Law_cuts_bit_size_to_12_atoms?taxonomyId=19","source":"computerworld.com","points":"8","comments":"4","submitter":"MrFacepalm","date":1326685952,"id":"3469190","homepage":false},{"link_text":"Friendsheet - A better Facebook photo browser","link":"http://www.friendsheet.com","source":"friendsheet.com","points":"13","comments":"14","submitter":"zachallia","date":1326684149,"id":"3469184","homepage":false},{"link_text":"The real deal with Groupon","link":"http://www.cbsnews.com/video/watch/?id=7395218n&tag=contentBody;storyMediaBox","source":"cbsnews.com","points":"30","comments":"24","submitter":"pitdesi","date":1326680249,"id":"3468985","homepage":false},{"link_text":"Zappos: Security Email","link":"http://blogs.zappos.com/securityemail","source":"zappos.com","points":"7","comments":"1","submitter":"rmurphey3","date":1326680249,"id":"3468984","homepage":false},{"link_text":"Zappos.com customer database compromised","link":"http://www.zappos.com/passwordchange","source":"zappos.com","points":"199","comments":"87","submitter":"clamstar","date":1326678748,"id":"3468974","homepage":false},{"link_text":"An Investment Manager's View on the Top 1%","link":"http://www2.ucsc.edu/whorulesamerica/power/investment_manager.html","source":"ucsc.edu","points":"195","comments":"64","submitter":"niels_olson","date":1326678449,"id":"3468797","homepage":false},{"link_text":"Startups: Don't Host Your Blog on Tumblr","link":"http://blog.picplum.com/startups-dont-host-your-blog-on-tumblr/","source":"picplum.com","points":"160","comments":"86","submitter":"PStamatiou","date":1326676349,"id":"3468879","homepage":false},{"link_text":"Diablo II postmortem by one of the creators","link":"http://www.gamasutra.com/view/feature/3124/postmortem_blizzards_diablo_ii.php","source":"gamasutra.com","points":"12","comments":"1","submitter":"voberoi","date":1326676049,"id":"3468835","homepage":false},{"link_text":"Color schemes I can feel","link":"http://design-seeds.com","source":"design-seeds.com","points":"124","comments":"24","submitter":"aymeric","date":1326676049,"id":"3468517","homepage":false},{"link_text":"Best TLD that can't be taken down by US/etc?","link":"http://news.ycombinator.com/item?id=3468595","points":"67","comments":"36","submitter":"Andrenid","date":1326672668,"id":"3468595","homepage":false},{"link_text":"Selling a 300-Year-Old Cello","link":"http://www.nytimes.com/2012/01/15/magazine/bernard-greenhouse-cello.html?_r=2&pagewanted=all","source":"nytimes.com","points":"40","comments":"23","submitter":"pg","date":1326672367,"id":"3468551","homepage":false},{"link_text":"Startup will wash your car wherever it is located","link":"http://cherry.com/","source":"cherry.com","points":"122","comments":"94","submitter":"pitdesi","date":1326672067,"id":"3468646","homepage":false}]