[{"link_text":"Android account passwords are stored on disk in plain text","link":"http://code.google.com/p/android/issues/detail?id=10809","source":"google.com","points":"186","comments":"88","submitter":"wheels","date":1311377408,"id":"2795552","homepage":false},{"link_text":"On Succeeding Steve Jobs","link":"http://daringfireball.net/2011/07/succeeding_steve_jobs","source":"daringfireball.net","points":"221","comments":"103","submitter":"ddagradi","date":1311375008,"id":"2795411","homepage":false},{"link_text":"Serial cable for iPod approved by Apple","link":"http://www.makershed.com/ProductDetails.asp?ProductCode=MSRP01&Click=85531&utm_medium=email&utm_campaign=Maker+Shed+Jul+21+2011&utm_content=Maker+Shed+Jul+21+2011+CID_5d19bd49d4c9737785f05cd1d70cd693&utm_source=Email+Campaign&utm_term=cable","source":"makershed.com","points":"77","comments":"66","submitter":"dholowiski","date":1311372008,"id":"2795287","homepage":false},{"link_text":"How 38 Monks Took on the Funeral Cartel and Won","link":"http://www.theatlantic.com/national/archive/2011/07/how-38-monks-took-on-the-funeral-cartel-and-won/242336/","source":"theatlantic.com","points":"121","comments":"28","submitter":"YetAnotherAlias","date":1311370808,"id":"2794793","homepage":false},{"link_text":"Apple’s full change log for iOS 5 beta 4","link":"http://www.bgr.com/2011/07/22/apples-full-change-log-for-ios-5-beta-4/","source":"bgr.com","points":"10","comments":"2","submitter":"zacharye","date":1311370508,"id":"2795196","homepage":false},{"link_text":"IOS 5 beta 4 is out","link":"http://developer.apple.com/library/prerelease/ios/#releasenotes/General/RN-iOSSDK-5_0/_index.html","source":"apple.com","points":"42","comments":"17","submitter":"hemancuso","date":1311368108,"id":"2795133","homepage":false},{"link_text":"Y Combinator Taps Into Its Alumni Network, Announces Ad Innovation Conference","link":"http://techcrunch.com/2011/07/22/y-combinator-taps-into-its-alumni-network-announces-ad-innovation-conference/","source":"techcrunch.com","points":"51","comments":"6","submitter":"hydrazine","date":1311365708,"id":"2794806","homepage":false},{"link_text":"First Twitter Engineer Does it Again, Secures 2 Million, Amen.","link":"http://eu.techcrunch.com/2011/07/22/ashton-kutcher-and-madonnas-manager-invest-in-tiny-berlin-startup-what-gives/","source":"techcrunch.com","points":"13","comments":"6","submitter":"iSimone","date":1311364208,"id":"2794833","homepage":false},{"link_text":"Is Pre-Cognition Possible & Can It Beat Twitter on Breaking News?","link":"http://www.readwriteweb.com/archives/is_pre-cognition_possible_can_it_beat_twitter_on_b.php#.TinLzcgLEmQ.hackernews","source":"readwriteweb.com","points":"10","comments":"1","submitter":"duzins","date":1311363608,"id":"2794792","homepage":false},{"link_text":"Android Jobs to Surpass iPhone Jobs by Year-End","link":"http://www.readwriteweb.com/mobile/2011/07/android-jobs-to-surpass-iphone-jobs-by-year-end-report-finds.php#.TinNIgsXIqs.hackernews","source":"readwriteweb.com","points":"8","comments":"3","submitter":"duzins","date":1311362708,"id":"2794825","homepage":false},{"link_text":"Yes, Google Chrome Built For OS X Lion Is Coming — But It Will Take Time","link":"http://techcrunch.com/2011/07/21/chrome-os-x-lion/","source":"techcrunch.com","points":"26","comments":"7","submitter":"amyshelton","date":1311362408,"id":"2794759","homepage":false},{"link_text":"What everyone should know about the human eye","link":"http://www.gazehawk.com/blog/what-everyone-should-know-about-the-human-eye/","source":"gazehawk.com","points":"253","comments":"46","submitter":"bkrausz","date":1311361228,"id":"2794717","homepage":false},{"link_text":"An amazing crossword puzzle","link":"http://kottke.org/11/07/an-amazing-crossword-puzzle","source":"kottke.org","points":"74","comments":"10","submitter":"superchink","date":1311360909,"id":"2794642","homepage":false},{"link_text":"Ad Innovation Conference, September 14 at YC","link":"http://adinnovationconference.com/","source":"adinnovationconference.com","points":"101","comments":"23","submitter":"jl","date":1311360310,"id":"2794646","homepage":false},{"link_text":"JavaScript Creator Says the Language Wasn't Just Dumb Luck","link":"http://www.readwriteweb.com/hack/2011/07/javascript-was-no-accident.php","source":"readwriteweb.com","points":"68","comments":"11","submitter":"PixelRobot","date":1311359108,"id":"2794543","homepage":false},{"link_text":"DoD offers up tiny, secure Linux distro","link":"http://www.geek.com/articles/chips/u-s-dept-of-defense-offers-up-tiny-secure-linux-distribution-20110722/","source":"geek.com","points":"53","comments":"30","submitter":"thomas","date":1311359108,"id":"2794540","homepage":false},{"link_text":"Google Deletes Last 7 Years Of User's Digital Life, Shrugs","link":"http://consumerist.com/2011/07/google-deletes-last-7-years-of-users-digital-life-shrugs.html","source":"consumerist.com","points":"294","comments":"225","submitter":"tshtf","date":1311359108,"id":"2794529","homepage":false},{"link_text":"Didn't Get Into TechStars? Don't Sweat it","link":"http://www.currentlyobsessed.com/2011/07/22/didnt-get-into-techstars-dont-sweat-it/","source":"currentlyobsessed.com","points":"32","comments":"28","submitter":"kirillzubovsky","date":1311358208,"id":"2794477","homepage":false},{"link_text":"Out Of The Blue, Instacolor Forced To Change Name By The “True” Color","link":"http://techcrunch.com/2011/07/22/out-of-the-blue-instacolor-forced-to-change-name-by-the-true-color/","source":"techcrunch.com","points":"11","comments":"4","submitter":"palebluedot","date":1311357308,"id":"2794460","homepage":false},{"link_text":"Big Content's latest antipiracy weapon: extradition","link":"http://arstechnica.com/tech-policy/news/2011/07/big-content-unveils-latest-antipiracy-weapon-extradition.ars/1","source":"arstechnica.com","points":"44","comments":"4","submitter":"timwiseman","date":1311357024,"id":"2794273","homepage":false},{"link_text":"The future of following","link":"http://scripting.com/stories/2011/07/22/sharingListsOfFriends.html","source":"scripting.com","points":"3","comments":"1","submitter":"davewiner","date":1311355508,"id":"2794316","homepage":false},{"link_text":"Min.us is now Minus.com","link":"http://minus.com","source":"minus.com","points":"6","comments":"2","submitter":"mindotus","date":1311354908,"id":"2794318","homepage":false},{"link_text":"$2,000 in prize money for StartupHouse 24 Hr Challenge Hackathon Tonight in SF","link":"http://go.getsocialize.com/24-hour-challenge","source":"getsocialize.com","points":"6","comments":"2","submitter":"danielodio","date":1311354316,"id":"2794261","homepage":false},{"link_text":"Google & Facebook Set Company Records for Lobbyist Spending","link":"http://mashable.com/2011/07/21/google-facebook-set-company-records-for-lobbyist-spending/","source":"mashable.com","points":"7","comments":"2","submitter":"tilt","date":1311353709,"id":"2794228","homepage":false},{"link_text":"Two special startup types: the Twitter and the Hoverboard","link":"http://www.danshapiro.com/blog/2011/07/a-twitter-a-hoverboard-or-something-in-between/","source":"danshapiro.com","points":"46","comments":"13","submitter":"danshapiro","date":1311353408,"id":"2794219","homepage":false},{"link_text":"Diamonds are not formed from coal under heat and pressure","link":"http://arstechnica.com/science/news/2011/07/plate-tectonics-different-on-early-earth.ars","source":"arstechnica.com","points":"14","comments":"13","submitter":"shawndumas","date":1311353408,"id":"2794096","homepage":false},{"link_text":"Google account gets blocked without explanation","link":"http://www.twitlonger.com/show/bsdnia","source":"twitlonger.com","points":"42","comments":"33","submitter":"narad","date":1311352508,"id":"2793784","homepage":false},{"link_text":"Lion removes Java?","link":"http://lookfirst.com/2011/07/lion-removes-java.html","source":"lookfirst.com","points":"59","comments":"80","submitter":"latchkey","date":1311351008,"id":"2794081","homepage":false},{"link_text":"U.S. Blocks Oversight of Its Mercenary Army in Iraq","link":"http://www.wired.com/dangerroom/2011/07/iraq-merc-army/","source":"wired.com","points":"7","comments":"0","submitter":"llambda","date":1311350708,"id":"2794012","homepage":false},{"link_text":"This is how you leave a company","link":"https://gist.github.com/9cfe62fe0ba1348aa670","source":"github.com","points":"5","comments":"1","submitter":"danryan","date":1311350108,"id":"2793957","homepage":false},{"link_text":"A Bomb in Oslo? What Google Lost by Ending Real-Time Search","link":"http://www.theatlantic.com/technology/archive/2011/07/a-bomb-in-oslo-what-google-lost-by-ending-real-time-search/242357/","source":"theatlantic.com","points":"83","comments":"34","submitter":"nbj914","date":1311348609,"id":"2793869","homepage":false},{"link_text":"Limelight creates a beautiful site for your apps in seconds.","link":"http://limelightapp.com/","source":"limelightapp.com","points":"31","comments":"24","submitter":"aculver","date":1311348309,"id":"2793853","homepage":false},{"link_text":"Urbanisation in Minecraft","link":"http://crafthub.net/2011/07/22/urbanisation-in-minecraft/","source":"crafthub.net","points":"128","comments":"55","submitter":"rcfox","date":1311347708,"id":"2793768","homepage":false},{"link_text":"NY Ousts Boston as No.2 Tech Hub","link":"http://bostinnovation.com/2011/07/22/new-york-ousts-boston-as-no-2-tech-hub/","source":"bostinnovation.com","points":"20","comments":"9","submitter":"ekm","date":1311347408,"id":"2793604","homepage":false},{"link_text":"The Brilliance of Dwarf Fortress","link":"http://www.nytimes.com/2011/07/24/magazine/the-brilliance-of-dwarf-fortress.html?_r=1&ref=technology&pagewanted=all","source":"nytimes.com","points":"409","comments":"135","submitter":"pcestrada","date":1311347108,"id":"2793615","homepage":false},{"link_text":"Microsoft posts record revenue in spite of flat Windows market","link":"http://arstechnica.com/#!/microsoft/news/2011/07/microsoft-posts-record-revenue-in-spite-of-flat-windows-market.ars","source":"arstechnica.com","points":"39","comments":"16","submitter":"evo_9","date":1311346508,"id":"2793576","homepage":false},{"link_text":"Agility.js - Javascript MVC for the \"write less, do more\" programmer","link":"http://agilityjs.com","source":"agilityjs.com","points":"103","comments":"33","submitter":"arturadib","date":1311345908,"id":"2793634","homepage":false},{"link_text":"Toyota automatically stops car before it can hit pedestrian","link":"http://www.networkworld.com/community/blog/toyota-system-automatically-stops-car-it-hits","source":"networkworld.com","points":"31","comments":"68","submitter":"buzzblog","date":1311345308,"id":"2793553","homepage":false},{"link_text":"The Rise of Google+: Email is Social’s Secret Weapon","link":"http://www.betabeat.com/2011/07/22/the-fall-of-aol-bebo-and-the-rise-of-google-email-is-social-dummies/","source":"betabeat.com","points":"61","comments":"26","submitter":"jonbot","date":1311344409,"id":"2793579","homepage":false},{"link_text":"Samsung’s Galaxy S II invades the US in August","link":"http://venturebeat.com/2011/07/20/samsung-galaxy-s-ii-us-launch/","source":"venturebeat.com","points":"14","comments":"14","submitter":"richardofyork","date":1311344409,"id":"2793549","homepage":false},{"link_text":"Graph: How long it took Facebook, Twitter and Google+ to reach 10 million users","link":"http://eu.techcrunch.com/2011/07/22/graph-how-long-it-took-facebook-twitter-and-google-to-reach-10-million-users/","source":"techcrunch.com","points":"63","comments":"37","submitter":"aditiyaa1","date":1311344409,"id":"2793496","homepage":false},{"link_text":"Researchers create tattoo that tracks sodium and glucose via iPhone","link":"http://bostinnovation.com/2011/07/22/northeastern-creates-tattoo-that-tracks-sodium-and-glucose-via-an-iphone/","source":"bostinnovation.com","points":"102","comments":"26","submitter":"jerrelp","date":1311344108,"id":"2793522","homepage":false},{"link_text":"Phono Mobile is now available on iOS and Android platforms thanks to PhoneGap","link":"http://phono.com/mobile","source":"phono.com","points":"18","comments":"0","submitter":"cmatthieu","date":1311344108,"id":"2793459","homepage":false},{"link_text":"NASA's Successful Quantifying of Comedy Timing (By Penn Jillette and Teller)","link":"http://symftr.tumblr.com/post/5987695109/nasas-successful-quantifying-of-comedy-timing-by-penn","source":"symftr.tumblr.com","points":"220","comments":"30","submitter":"wallflower","date":1311343208,"id":"2793404","homepage":false},{"link_text":"Use pythonbrew to manage multiple python installations","link":"https://github.com/utahta/pythonbrew","source":"github.com","points":"48","comments":"14","submitter":"tdfx","date":1311342908,"id":"2793432","homepage":false},{"link_text":"Incorrect Core Java Interview Answers","link":"http://java.dzone.com/articles/incorrect-core-java-interview","source":"dzone.com","points":"15","comments":"13","submitter":"cfontes","date":1311342608,"id":"2793399","homepage":false},{"link_text":"Angry Birds maker Rovio sued over app patents","link":"http://www.bbc.co.uk/news/business-14245047","source":"bbc.co.uk","points":"37","comments":"47","submitter":"watkdab","date":1311342608,"id":"2793336","homepage":false},{"link_text":"A simple text-based todo editor for Eclipse","link":"http://sebastianbenz.de/a-simple-text-based-todo-editor-for-eclipse","source":"sebastianbenz.de","points":"10","comments":"5","submitter":"codeup","date":1311342315,"id":"2793268","homepage":false},{"link_text":"Firefox Add-on Warns When You Visit a Murdoch Owned Website","link":"http://newsjunkiepost.com/2011/07/21/new-firefox-add-on-warns-you-about-the-dangers-of-the-murdoch-propaganda-machine/","source":"newsjunkiepost.com","points":"35","comments":"15","submitter":"d0ne","date":1311341108,"id":"2793337","homepage":false},{"link_text":"A practical introduction to MochiWeb","link":"http://alexmarandon.com/articles/mochiweb_tutorial/","source":"alexmarandon.com","points":"32","comments":"0","submitter":"rhizome31","date":1311341108,"id":"2793219","homepage":false},{"link_text":"Does the infamous \"Happy Birthday to You\" copyright hold up to scrutiny?","link":"http://www.slate.com/id/2298271/pagenum/all","source":"slate.com","points":"72","comments":"20","submitter":"JacobAldridge","date":1311339908,"id":"2793184","homepage":false},{"link_text":"Stop hating Java","link":"http://andrzejonsoftware.blogspot.com/2011/07/stop-hating-java.html","source":"andrzejonsoftware.blogspot.com","points":"106","comments":"148","submitter":"snatcher","date":1311339308,"id":"2793227","homepage":false},{"link_text":"AP Finally Learns that You Can Link to Other Sites on the Internet","link":"http://www.techdirt.com/articles/20110720/15543515185/ap-finally-learns-that-internet-you-can-link-to-other-sites.shtml","source":"techdirt.com","points":"58","comments":"18","submitter":"jsherry","date":1311337808,"id":"2793165","homepage":false},{"link_text":"First HN Meeting in Paris: story and pics","link":"http://blog.medusis.com/first-paris-hackers-meetup","source":"medusis.com","points":"55","comments":"22","submitter":"bambax","date":1311336308,"id":"2793118","homepage":false},{"link_text":"Github Meets CPAN: Ranking","link":"http://www.github-meets-cpan.com/","source":"github-meets-cpan.com","points":"7","comments":"2","submitter":"draegtun","date":1311335708,"id":"2793026","homepage":false},{"link_text":"Chosen: A javascript plug-in that makes long select boxes user-friendly.","link":"http://harvesthq.github.com/chosen","source":"github.com","points":"892","comments":"76","submitter":"utkarshkukreti","date":1311335108,"id":"2793086","homepage":false},{"link_text":"EBay Patents 10-Click Checkout","link":"http://steve-yegge.blogspot.com/2011/07/ebay-patents-10-click-checkout.html","source":"steve-yegge.blogspot.com","points":"330","comments":"39","submitter":"timruffles","date":1311335108,"id":"2793039","homepage":false},{"link_text":"How To Manage Geeks","link":"http://www.wikihow.com/Manage-Geeks","source":"wikihow.com","points":"68","comments":"30","submitter":"trueduke","date":1311335108,"id":"2792936","homepage":false},{"link_text":"Ask HN: Ideas on how to change the Culture at a big Corporate Bank","link":"http://news.ycombinator.com/item?id=2792985","points":"13","comments":"23","submitter":"sw1205","date":1311333609,"id":"2792985","homepage":false},{"link_text":"Fusker - a NodeJS security system that attacks back","link":"https://github.com/wearefractal/fusker","source":"github.com","points":"68","comments":"30","submitter":"mikaelchoni","date":1311330309,"id":"2792942","homepage":false},{"link_text":"Adobe releases lengthy list of Apple Lion woes","link":"http://www.theregister.co.uk/2011/07/21/adobe_lion_incompatibilities/","source":"theregister.co.uk","points":"27","comments":"23","submitter":"zachinglis","date":1311325208,"id":"2792782","homepage":false},{"link_text":"Secure Apache and PHP, hide version numbers","link":"http://www.go2linux.org/linux/2011/07/secure-apache-and-php-hide-version-numbers-1122.html","source":"go2linux.org","points":"4","comments":"10","submitter":"darkduck","date":1311323708,"id":"2792722","homepage":false},{"link_text":"Newt Gingrich's Drupal website cost $800,000","link":"http://www.epolitics.com/2011/07/18/newt-gingrichs-800000-tiffany-website-puts-his-campaign-into-debt/","source":"epolitics.com","points":"5","comments":"0","submitter":"rdoherty","date":1311317108,"id":"2792563","homepage":false},{"link_text":"Alexander Calder-themed Google","link":"http://www.google.com/?calder","source":"google.com","points":"15","comments":"5","submitter":"sahillavingia","date":1311314710,"id":"2792458","homepage":false},{"link_text":"Ideas on how to get into kernel hacking","link":"http://kernelnewbies.org/CompleteNewbiesClickHere","source":"kernelnewbies.org","points":"15","comments":"0","submitter":"thmzlt","date":1311313810,"id":"2792510","homepage":false},{"link_text":"Linux 3.0 tagged","link":"http://git.kernel.org/?p=linux/kernel/git/torvalds/linux-2.6.git;a=tag;h=refs/tags/v3.0","source":"kernel.org","points":"17","comments":"0","submitter":"ethereal","date":1311309009,"id":"2792405","homepage":false},{"link_text":"Anonymous Hacks NATO, Steals GB Of Data","link":"http://www.crn.com/news/security/231002347/anonymous-hacks-nato-steals-gb-of-data.htm","source":"crn.com","points":"86","comments":"29","submitter":"Garbage","date":1311309009,"id":"2792322","homepage":false},{"link_text":"Linux 3.0 release","link":"http://lwn.net/Articles/452531/","source":"lwn.net","points":"184","comments":"16","submitter":"timf","date":1311308710,"id":"2792403","homepage":false},{"link_text":"Go for App Engine is now generally available","link":"http://blog.golang.org/2011/07/go-for-app-engine-is-now-generally.html","source":"golang.org","points":"68","comments":"25","submitter":"enneff","date":1311307510,"id":"2792351","homepage":false},{"link_text":"Memberly - helps creative ppl run subscription programs","link":"http://member.ly/","source":"member.ly","points":"14","comments":"6","submitter":"ericelias","date":1311307210,"id":"2792130","homepage":false},{"link_text":"blitz.io node.js client","link":"https://github.com/ghermeto/blitz-node","source":"github.com","points":"6","comments":"1","submitter":"ghermeto","date":1311305409,"id":"2792211","homepage":false},{"link_text":"Apple to Buy Hulu? ","link":"http://mashable.com/2011/07/21/apple-to-buy-hulu/","source":"mashable.com","points":"47","comments":"21","submitter":"jedwhite","date":1311305111,"id":"2792264","homepage":false},{"link_text":"Writing Elegant Clojure Code Using Higher-Order Functions","link":"http://christophermaier.name/2011/07/07/writing-elegant-clojure-code-using-higher-order-functions.html","source":"christophermaier.name","points":"29","comments":"8","submitter":"mblakele","date":1311304810,"id":"2792251","homepage":false},{"link_text":"Head JS Loads JavaScript Files Like Images Without Blocking the Page","link":"http://headjs.com/#","source":"headjs.com","points":"67","comments":"14","submitter":"wslh","date":1311304810,"id":"2792170","homepage":false},{"link_text":"There's Going To Be An Implosion And A Major Shakeout In The Industry","link":"http://www.businessinsider.com/ex-living-social-sales-guy-theres-going-to-be-an-implosion-and-a-major-shakeout-in-the-industry-2011-7","source":"businessinsider.com","points":"7","comments":"0","submitter":"wslh","date":1311302709,"id":"2792145","homepage":false},{"link_text":"30 Login Forms with Creative Design","link":"http://speckyboy.com/2011/07/21/30-login-forms-with-creative-design/","source":"speckyboy.com","points":"4","comments":"1","submitter":"wslh","date":1311302409,"id":"2792118","homepage":false},{"link_text":"Use Lion's emoji to hack Google ads","link":"http://blog.mixrank.com/google-hack-lets-you-include-images-in-search","source":"mixrank.com","points":"13","comments":"4","submitter":"smilliken","date":1311301209,"id":"2792094","homepage":false},{"link_text":"Judge criticizes Google and Oracle at hearing","link":"http://www.reuters.com/article/2011/07/21/us-oracle-google-lawsuit-idUSTRE76K7U820110721","source":"reuters.com","points":"52","comments":"25","submitter":"kenjackson","date":1311299410,"id":"2792003","homepage":false},{"link_text":"Rackspace going all OpenStack","link":"http://www.networkworld.com/news/2011/072111-rackspace-cloud-openstack.html","source":"networkworld.com","points":"9","comments":"0","submitter":"j_baker","date":1311299410,"id":"2791930","homepage":false},{"link_text":"NYU Prof Vows Never to Probe Cheating Again—and Faces a Backlash","link":"http://chronicle.com/blogs/wiredcampus/nyu-prof-vows-never-to-probe-cheating-again%E2%80%94and-faces-a-backlash/32351","source":"chronicle.com","points":"192","comments":"108","submitter":"ilamont","date":1311299110,"id":"2792007","homepage":false},{"link_text":"Wikipedia: Making of Doom","link":"http://en.wikipedia.org/wiki/Making_of_Doom#Programming","source":"wikipedia.org","points":"94","comments":"32","submitter":"olliesaunders","date":1311298510,"id":"2791970","homepage":false},{"link_text":"Race to Moon by Private Companies","link":"http://www.nytimes.com/2011/07/22/science/space/22moon.html?_r=1&pagewanted=all","source":"nytimes.com","points":"74","comments":"20","submitter":"jamesbritt","date":1311298209,"id":"2791995","homepage":false},{"link_text":"Polyglot programming - combining functional, dynamic and imperative languages","link":"http://www.mindscapehq.com/blog/index.php/2011/07/21/polyglot-programming-some-lessons-learned/","source":"mindscapehq.com","points":"40","comments":"3","submitter":"traskjd","date":1311297916,"id":"2791977","homepage":false},{"link_text":"Greece defaults","link":"http://blogs.reuters.com/felix-salmon/2011/07/21/greece-defaults/","source":"reuters.com","points":"490","comments":"142","submitter":"MaysonL","date":1311293410,"id":"2791778","homepage":false},{"link_text":"Do Authors Dream of Electric Book Signings?","link":"http://techcrunch.com/2011/07/21/do-authors-dream-of-electric-book-signings-kindlegraph-hopes-so/","source":"techcrunch.com","points":"4","comments":"2","submitter":"evanjacobs","date":1311293110,"id":"2791812","homepage":false},{"link_text":"SproutCore 2.0 Beta 2 Released","link":"http://blog.sproutcore.com/sproutcore-2-0-beta-2-released/","source":"sproutcore.com","points":"55","comments":"4","submitter":"madouglas","date":1311292810,"id":"2791794","homepage":false}]